qiskit/ignis/VERSION.txt
qiskit/ignis/__init__.py
qiskit/ignis/numba.py
qiskit/ignis/utils.py
qiskit/ignis/version.py
qiskit/ignis/characterization/__init__.py
qiskit/ignis/characterization/characterization_utils.py
qiskit/ignis/characterization/fitters.py
qiskit/ignis/characterization/calibrations/__init__.py
qiskit/ignis/characterization/calibrations/fitters.py
qiskit/ignis/characterization/calibrations/ibmq_utils.py
qiskit/ignis/characterization/calibrations/pulse_schedules.py
qiskit/ignis/characterization/coherence/__init__.py
qiskit/ignis/characterization/coherence/circuits.py
qiskit/ignis/characterization/coherence/fitters.py
qiskit/ignis/characterization/gates/__init__.py
qiskit/ignis/characterization/gates/circuits.py
qiskit/ignis/characterization/gates/fitters.py
qiskit/ignis/characterization/hamiltonian/__init__.py
qiskit/ignis/characterization/hamiltonian/circuits.py
qiskit/ignis/characterization/hamiltonian/fitters.py
qiskit/ignis/logging/__init__.py
qiskit/ignis/logging/ignis_logging.py
qiskit/ignis/measurement/__init__.py
qiskit/ignis/measurement/discriminator/__init__.py
qiskit/ignis/measurement/discriminator/discriminators.py
qiskit/ignis/measurement/discriminator/filters.py
qiskit/ignis/measurement/discriminator/iq_discriminators.py
qiskit/ignis/mitigation/__init__.py
qiskit/ignis/mitigation/expval/__init__.py
qiskit/ignis/mitigation/expval/base_meas_mitigator.py
qiskit/ignis/mitigation/expval/circuits.py
qiskit/ignis/mitigation/expval/complete_mitigator.py
qiskit/ignis/mitigation/expval/ctmp_fitter.py
qiskit/ignis/mitigation/expval/ctmp_generator_set.py
qiskit/ignis/mitigation/expval/ctmp_mitigator.py
qiskit/ignis/mitigation/expval/fitter.py
qiskit/ignis/mitigation/expval/tensored_mitigator.py
qiskit/ignis/mitigation/expval/utils.py
qiskit/ignis/mitigation/measurement/__init__.py
qiskit/ignis/mitigation/measurement/circuits.py
qiskit/ignis/mitigation/measurement/filters.py
qiskit/ignis/mitigation/measurement/fitters.py
qiskit_ignis-0.7.1.dist-info/LICENSE.txt
qiskit_ignis-0.7.1.dist-info/METADATA
qiskit_ignis-0.7.1.dist-info/WHEEL
qiskit_ignis-0.7.1.dist-info/top_level.txt
qiskit_ignis-0.7.1.dist-info/RECORD
